adafruit_midi_parser.py
adafruit_circuitpython_midi_parser-1.2.1.dist-info/licenses/LICENSE
adafruit_circuitpython_midi_parser-1.2.1.dist-info/METADATA
adafruit_circuitpython_midi_parser-1.2.1.dist-info/WHEEL
adafruit_circuitpython_midi_parser-1.2.1.dist-info/top_level.txt
adafruit_circuitpython_midi_parser-1.2.1.dist-info/RECORD
