Metadata-Version: 2.4
Name: adafruit-circuitpython-midi-parser
Version: 1.2.1
Summary: CircuitPython helper for parsing MIDI files
Author-email: Adafruit Industries <circuitpython@adafruit.com>
License: MIT
Project-URL: Homepage, https://github.com/adafruit/Adafruit_CircuitPython_MIDI_Parser
Keywords: adafruit,blinka,circuitpython,micropython,midi_parser,MIDI
Classifier: Intended Audience :: Developers
Classifier: Topic :: Software Development :: Libraries
Classifier: Topic :: Software Development :: Embedded Systems
Classifier: Topic :: System :: Hardware
Classifier: License :: OSI Approved :: MIT License
Classifier: Programming Language :: Python :: 3
License-File: LICENSE
Requires-Dist: Adafruit-Blinka
Provides-Extra: optional
Dynamic: license-file
